{"id":"bd8aad87baae46c9b636514afd251968","source_id_to_path":{"0":"lib/forge-std/src/Base.sol","1":"lib/forge-std/src/StdAssertions.sol","2":"lib/forge-std/src/StdChains.sol","3":"lib/forge-std/src/StdCheats.sol","4":"lib/forge-std/src/StdError.sol","5":"lib/forge-std/src/StdInvariant.sol","6":"lib/forge-std/src/StdJson.sol","7":"lib/forge-std/src/StdMath.sol","8":"lib/forge-std/src/StdStorage.sol","9":"lib/forge-std/src/StdStyle.sol","10":"lib/forge-std/src/StdToml.sol","11":"lib/forge-std/src/StdUtils.sol","12":"lib/forge-std/src/Test.sol","13":"lib/forge-std/src/Vm.sol","14":"lib/forge-std/src/console.sol","15":"lib/forge-std/src/console2.sol","16":"lib/forge-std/src/interfaces/IERC165.sol","17":"lib/forge-std/src/interfaces/IERC20.sol","18":"lib/forge-std/src/interfaces/IERC721.sol","19":"lib/forge-std/src/interfaces/IMulticall3.sol","20":"lib/forge-std/src/mocks/MockERC20.sol","21":"lib/forge-std/src/mocks/MockERC721.sol","22":"lib/forge-std/src/safeconsole.sol","23":"src/Constants.sol","24":"src/exercises/Borrow.sol","25":"src/exercises/Flash.sol","26":"src/exercises/Liquidate.sol","27":"src/exercises/LongShort.sol","28":"src/exercises/Repay.sol","29":"src/exercises/Supply.sol","30":"src/exercises/Withdraw.sol","31":"src/interfaces/IERC20.sol","32":"src/interfaces/aave-v3/IAaveOracle.sol","33":"src/interfaces/aave-v3/IPool.sol","34":"src/interfaces/aave-v3/IVariableDebtToken.sol","35":"src/interfaces/uniswap-v3/ISwapRouter.sol","36":"src/lib/Aave.sol","37":"src/lib/Math.sol","38":"src/lib/Swap.sol","39":"src/solutions/Borrow.sol","40":"src/solutions/Flash.sol","41":"src/solutions/Liquidate.sol","42":"src/solutions/LongShort.sol","43":"src/solutions/Repay.sol","44":"src/solutions/Supply.sol","45":"src/solutions/Withdraw.sol","46":"test/Borrow.test.sol","47":"test/Flash.test.sol","48":"test/Liquidate.test.sol","49":"test/LongShort.test.sol","50":"test/Repay.test.sol","51":"test/Supply.test.sol","52":"test/Withdraw.test.sol"},"language":"Solidity"}